fastapi_utk/__init__.py
fastapi_utk/middleware/__init__.py
fastapi_utk/middleware/camel_case_query_params.py
fastapi_utk/not_set/__init__.py
fastapi_utk/not_set/not_set.py
fastapi_utk/openapi/__init__.py
fastapi_utk/openapi/translate_query_params_snake_to_camel.py
fastapi_utk/openapi/types.py
fastapi_utk/pagination/__init__.py
fastapi_utk/pagination/config.py
fastapi_utk/pagination/paginator.py
fastapi_utk/pagination/response.py
fastapi_utk/sorting/__init__.py
fastapi_utk/sorting/config.py
fastapi_utk/sorting/sorting.py
fastapi_utk/strings/__init__.py
fastapi_utk/strings/uuid.py
fastapi_utk-1.0.3.dist-info/licenses/LICENSE
fastapi_utk-1.0.3.dist-info/METADATA
fastapi_utk-1.0.3.dist-info/WHEEL
fastapi_utk-1.0.3.dist-info/top_level.txt
fastapi_utk-1.0.3.dist-info/RECORD
