Metadata-Version: 2.4
Name: fastapi-utk
Version: 1.0.3
Summary: FastAPI Ultimate Toolkit
Author-email: v1a0 <contact@v1a0.dev>
Project-URL: homepage, https://github.com/v1a0/fastapi-utk
Project-URL: example, https://github.com/v1a0/fastapi-utk/tree/main/example
Classifier: Programming Language :: Python :: 3.13
Classifier: Framework :: FastAPI
Classifier: License :: OSI Approved :: GNU General Public License v3 (GPLv3)
Classifier: Operating System :: OS Independent
Requires-Python: >=3.12
License-File: LICENSE
Requires-Dist: fastapi>=0.115.12
Requires-Dist: pydantic>=2.11.5
Dynamic: license-file
